MANIFEST.in
setup.cfg
setup.py
Py_GP.egg-info/PKG-INFO
Py_GP.egg-info/SOURCES.txt
Py_GP.egg-info/dependency_links.txt
Py_GP.egg-info/requires.txt
Py_GP.egg-info/top_level.txt
pygp/__init__.py
pygp/constants.py
pygp/crypto.py
pygp/error.py
pygp/loadfile.py
pygp/logger.py
pygp/pygp.py
pygp/tlv.py
pygp/utils.py
pygp/connection/__init__.py
pygp/connection/connection.py
pygp/connection/pcscconnection.py
pygp/connection/pcsc/__init__.py
pygp/connection/pcsc/_scard.cp35-win32.pyd
pygp/connection/pcsc/_scard.pyd
pygp/connection/pcsc/scard.py
pygp/gp/__init__.py
pygp/gp/gp_crypto.py
pygp/gp/gp_functions.py
pygp/gp/gp_utils.py